Workbook

Sheet Welcome
A1: Domonique Excel Master Workbook — Business Analyst Training
A3: Fictional Company | B3: TechNova Solutions
A4: Purpose | B4: Practice Excel using realistic business data and interview-ready business scenarios.
A5: How to Use | B5: Start with XLOOKUP, then SUMIFS, COUNTIFS, Conditional Formatting, PivotTables, and Dashboard building.
A6: Portfolio Goal | B6: Turn this into an Excel business analysis project with a Loom walkthrough and GitHub documentation.
A9: Learning Roadmap | B9: Status | C9: Business Skill | D9: Excel Skill | E9: Interview Skill | F9: Portfolio Evidence | G9: Salesforce/SOQL Connection | H9: Notes
A10: 1. XLOOKUP | B10: Ready | C10: Connect related data | D10: Lookup formulas | E10: Explain shared keys | F10: Before/after lookup screenshots | G10: Similar to relationships using IDs
A11: 2. SUMIFS | B11: Ready | C11: Calculate revenue by criteria | D11: Conditional sums | E11: Explain metric + condition | F11: Revenue summary | G11: Similar to SUM + WHERE
A12: 3. COUNTIFS | B12: Ready | C12: Count records by criteria | D12: Conditional counts | E12: Explain record counts | F12: Order volume summary | G12: Similar to COUNT + WHERE
A13: 4. Conditional Formatting | B13: Ready | C13: Identify exceptions quickly | D13: Highlight rules | E13: Explain visual risk flags | F13: High-value sales view | G13: Similar to list view filters
A14: 5. PivotTables | B14: Ready | C14: Summarize performance | D14: Rows/Values/Filters | E14: Explain grouped analysis | F14: Revenue by region/rep | G14: Similar to Salesforce reports
A15: 6. Executive Dashboard | B15: Starter | C15: Tell the story | D15: Charts/KPIs | E15: Present insight + action | F15: Dashboard screenshot | G15: Similar to Salesforce dashboards

Sheet Data_Dictionary
A1: Data Dictionary
A3: Sheet | B3: Field | C3: Definition | D3: Example | E3: Why It Matters | F3: Related Skill
A4: Orders_Practice | B4: Customer ID | C4: Shared key that connects Orders to Customers | D4: C001 | E4: Used for XLOOKUP | F4: XLOOKUP / Relationships
A5: Orders_Practice | B5: Product ID | C5: Shared key that connects Orders to Products | D5: P001 | E5: Used to retrieve product details | F5: XLOOKUP
A6: Orders_Practice | B6: Rep ID | C6: Shared key that connects Orders to Sales_Reps | D6: R001 | E6: Used to retrieve rep details | F6: XLOOKUP
A7: Orders_Practice | B7: Revenue | C7: Money generated from the order | D7: 2400 | E7: Used for sales performance | F7: SUMIFS / PivotTables
A8: Orders_Practice | B8: Profit | C8: Money kept after estimated cost | D8: 672 | E8: Shows business profitability | F8: SUMIFS / Dashboard
A9: Customers | B9: Industry | C9: Customer business type | D9: Healthcare | E9: Used for segmentation | F9: SUMIFS / COUNTIFS
A10: Sales_Reps | B10: Rep Region | C10: Primary region assigned to rep | D10: North | E10: Used for performance comparison | F10: PivotTables

Sheet Customers
A1: Customers Table
A3: Customer ID | B3: Customer Name | C3: State | D3: Region | E3: Industry | F3: Segment
A4: C001 | B4: Acme Manufacturing | C4: MI | D4: North | E4: Manufacturing | F4: Enterprise
A5: C002 | B5: Blue Sky Health | C5: CA | D5: West | E5: Retail | F5: SMB
A6: C003 | B6: GreenTech Systems | C6: TX | D6: South | E6: Healthcare | F6: Enterprise
A7: C004 | B7: Northwind Retail | C7: IL | D7: North | E7: Financial Services | F7: SMB
A8: C005 | B8: Summit Logistics | C8: MN | D8: North | E8: Healthcare | F8: SMB
A9: C006 | B9: Bright Solar | C9: NC | D9: South | E9: Manufacturing | F9: Enterprise
A10: C007 | B10: Metro Foods | C10: FL | D10: South | E10: Financial Services | F10: SMB
A11: C008 | B11: Pioneer Labs | C11: MA | D11: East | E11: Logistics | F11: SMB
A12: C009 | B12: Riverbend Education | C12: GA | D12: South | E12: Financial Services | F12: Mid-Market
A13: C010 | B13: Urban Finance | C13: CA | D13: West | E13: Technology | F13: SMB
A14: C011 | B14: Evergreen Medical | C14: CO | D14: West | E14: Healthcare | F14: SMB
... A53: C050 | B53: Legacy Foods | C53: NC | D53: South | E53: Manufacturing | F53: SMB

Sheet Products
A1: Products Table
A3: Product ID | B3: Product Name | C3: Category | D3: Unit Price | E3: Margin %
A4: P001 | B4: Laptop Pro 14 | C4: Hardware | D4: 1200 | E4: 0.28
A5: P002 | B5: Laptop Pro 16 | C5: Hardware | D5: 1800 | E5: 0.25
A6: P003 | B6: 27-inch Monitor | C6: Hardware | D6: 300 | E6: 0.3
A7: P004 | B7: Wireless Keyboard | C7: Accessory | D7: 70 | E7: 0.4
A8: P005 | B8: Wireless Mouse | C8: Accessory | D8: 35 | E8: 0.42
A9: P006 | B9: USB-C Docking Station | C9: Accessory | D9: 250 | E9: 0.35
A10: P007 | B10: Security Software | C10: Software | D10: 600 | E10: 0.65
A11: P008 | B11: CRM Add-on License | C11: Software | D11: 900 | E11: 0.7
A12: P009 | B12: Implementation Package | C12: Service | D12: 3500 | E12: 0.55
A13: P010 | B13: Training Package | C13: Service | D13: 1200 | E13: 0.6
A14: P011 | B14: Cloud Backup Plan | C14: Software | D14: 450 | E14: 0.62
A15: P012 | B15: Managed Support Plan | C15: Service | D15: 2200 | E15: 0.5
... A23: P020 | B23: Network Switch | C23: Hardware | D23: 900 | E23: 0.26

Sheet Sales_Reps
A1: Sales Reps Table
A3: Rep ID | B3: Sales Rep | C3: Rep Region | D3: Experience Level
A4: R001 | B4: Ava Johnson | C4: North | D4: Senior
A5: R002 | B5: Ben Carter | C5: South | D5: Mid
A6: R003 | B6: Cara Lee | C6: East | D6: Junior
A7: R004 | B7: Dan Miller | C7: West | D7: Senior
A8: R005 | B8: Mia Thompson | C8: North | D8: Mid
A9: R006 | B9: Noah Davis | C9: South | D9: Junior
A10: R007 | B10: Leah Wilson | C10: East | D10: Senior
A11: R008 | B11: Omar Brown | C11: West | D11: Mid

Sheet Orders_Practice
A1: Orders Practice
A3: Order ID | B3: Order Date | C3: Customer ID | D3: Product ID | E3: Rep ID | F3: Quantity | G3: Unit Price | H3: Discount | I3: Revenue | J3: Profit | K3: Status | L3: Customer Name | M3: State | N3: Region | O3: Industry | P3: Segment | Q3: Product Name | R3: Category | S3: Sales Rep | T3: Rep Region
A4: O00001 | B4: 46055 | C4: C037 | D4: P003 | E4: R006 | F4: 2 | G4: 300 | H4: 0.1 | I4: 540 | J4: 162 | K4: Closed Won
A5: O00002 | B5: 46131 | C5: C043 | D5: P016 | E5: R003 | F5: 5 | G5: 1100 | H5: 0.1 | I5: 4950 | J5: 3366 | K5: Closed Won
A6: O00003 | B6: 46155 | C6: C035 | D6: P007 | E6: R006 | F6: 6 | G6: 600 | H6: 0.05 | I6: 3420 | J6: 2223 | K6: Open
A7: O00004 | B7: 46164 | C7: C008 | D7: P008 | E7: R007 | F7: 1 | G7: 900 | H7: 0.1 | I7: 810 | J7: 567 | K7: Closed Won
A8: O00005 | B8: 46031 | C8: C038 | D8: P008 | E8: R001 | F8: 4 | G8: 900 | H8: 0 | I8: 3600 | J8: 2520 | K8: Closed Won
A9: O00006 | B9: 46056 | C9: C005 | D9: P017 | E9: R005 | F9: 4 | G9: 2800 | H9: 0.1 | I9: 10080 | J9: 5241.6 | K9: Closed Lost
A10: O00007 | B10: 46047 | C10: C037 | D10: P016 | E10: R006 | F10: 7 | G10: 1100 | H10: 0 | I10: 7700 | J10: 5236 | K10: Closed Won
A11: O00008 | B11: 46036 | C11: C043 | D11: P014 | E11: R007 | F11: 8 | G11: 650 | H11: 0.15 | I11: 4420 | J11: 1414.4 | K11: Closed Won
A12: O00009 | B12: 46071 | C12: C004 | D12: P013 | E12: R001 | F12: 4 | G12: 800 | H12: 0 | I12: 3200 | J12: 864 | K12: Closed Lost
A13: O00010 | B13: 46042 | C13: C029 | D13: P005 | E13: R006 | F13: 8 | G13: 35 | H13: 0 | I13: 280 | J13: 117.6 | K13: Open
A14: O00011 | B14: 46065 | C14: C036 | D14: P004 | E14: R001 | F14: 2 | G14: 70 | H14: 0 | I14: 140 | J14: 56 | K14: Open
A15: O00012 | B15: 46120 | C15: C032 | D15: P016 | E15: R006 | F15: 1 | G15: 1100 | H15: 0 | I15: 1100 | J15: 748 | K15: Closed Won
... A183: O00180 | B183: 46058 | C183: C030 | D183: P010 | E183: R007 | F183: 3 | G183: 1200 | H183: 0 | I183: 3600 | J183: 2160 | K183: Closed Won

Sheet Orders_Solution
A1: Orders Solution
A3: Order ID | B3: Order Date | C3: Customer ID | D3: Product ID | E3: Rep ID | F3: Quantity | G3: Unit Price | H3: Discount | I3: Revenue | J3: Profit | K3: Status | L3: Customer Name | M3: State | N3: Region | O3: Industry | P3: Segment | Q3: Product Name | R3: Category | S3: Sales Rep | T3: Rep Region
A4: O00001 | B4: 46055 | C4: C037 | D4: P003 | E4: R006 | F4: 2 | G4: 300 | H4: 0.1 | I4: 540 | J4: 162 | K4: Closed Won | L4: =_xludf.XLOOKUP(C4,Customers!$A$4:$A$53,Customers!$B$4:$B$53,"Not found") -> #NAME? | M4: =_xludf.XLOOKUP(C4,Customers!$A$4:$A$53,Customers!$C$4:$C$53,"Not found") -> #NAME? | N4: =_xludf.XLOOKUP(C4,Customers!$A$4:$A$53,Customers!$D$4:$D$53,"Not found") -> #NAME? | O4: =_xludf.XLOOKUP(C4,Customers!$A$4:$A$53,Customers!$E$4:$E$53,"Not found") -> #NAME? | P4: =_xludf.XLOOKUP(C4,Customers!$A$4:$A$53,Customers!$F$4:$F$53,"Not found") -> #NAME? | Q4: =_xludf.XLOOKUP(D4,Products!$A$4:$A$23,Products!$B$4:$B$23,"Not found") -> #NAME? | R4: =_xludf.XLOOKUP(D4,Products!$A$4:$A$23,Products!$C$4:$C$23,"Not found") -> #NAME? | S4: =_xludf.XLOOKUP(E4,Sales_Reps!$A$4:$A$11,Sales_Reps!$B$4:$B$11,"Not found") -> #NAME? | T4: =_xludf.XLOOKUP(E4,Sales_Reps!$A$4:$A$11,Sales_Reps!$C$4:$C$11,"Not found") -> #NAME?
A5: O00002 | B5: 46131 | C5: C043 | D5: P016 | E5: R003 | F5: 5 | G5: 1100 | H5: 0.1 | I5: 4950 | J5: 3366 | K5: Closed Won | L5: =_xludf.XLOOKUP(C5,Customers!$A$4:$A$53,Customers!$B$4:$B$53,"Not found") -> #NAME? | M5: =_xludf.XLOOKUP(C5,Customers!$A$4:$A$53,Customers!$C$4:$C$53,"Not found") -> #NAME? | N5: =_xludf.XLOOKUP(C5,Customers!$A$4:$A$53,Customers!$D$4:$D$53,"Not found") -> #NAME? | O5: =_xludf.XLOOKUP(C5,Customers!$A$4:$A$53,Customers!$E$4:$E$53,"Not found") -> #NAME? | P5: =_xludf.XLOOKUP(C5,Customers!$A$4:$A$53,Customers!$F$4:$F$53,"Not found") -> #NAME? | Q5: =_xludf.XLOOKUP(D5,Products!$A$4:$A$23,Products!$B$4:$B$23,"Not found") -> #NAME? | R5: =_xludf.XLOOKUP(D5,Products!$A$4:$A$23,Products!$C$4:$C$23,"Not found") -> #NAME? | S5: =_xludf.XLOOKUP(E5,Sales_Reps!$A$4:$A$11,Sales_Reps!$B$4:$B$11,"Not found") -> #NAME? | T5: =_xludf.XLOOKUP(E5,Sales_Reps!$A$4:$A$11,Sales_Reps!$C$4:$C$11,"Not found") -> #NAME?
A6: O00003 | B6: 46155 | C6: C035 | D6: P007 | E6: R006 | F6: 6 | G6: 600 | H6: 0.05 | I6: 3420 | J6: 2223 | K6: Open | L6: =_xludf.XLOOKUP(C6,Customers!$A$4:$A$53,Customers!$B$4:$B$53,"Not found") -> #NAME? | M6: =_xludf.XLOOKUP(C6,Customers!$A$4:$A$53,Customers!$C$4:$C$53,"Not found") -> #NAME? | N6: =_xludf.XLOOKUP(C6,Customers!$A$4:$A$53,Customers!$D$4:$D$53,"Not found") -> #NAME? | O6: =_xludf.XLOOKUP(C6,Customers!$A$4:$A$53,Customers!$E$4:$E$53,"Not found") -> #NAME? | P6: =_xludf.XLOOKUP(C6,Customers!$A$4:$A$53,Customers!$F$4:$F$53,"Not found") -> #NAME? | Q6: =_xludf.XLOOKUP(D6,Products!$A$4:$A$23,Products!$B$4:$B$23,"Not found") -> #NAME? | R6: =_xludf.XLOOKUP(D6,Products!$A$4:$A$23,Products!$C$4:$C$23,"Not found") -> #NAME? | S6: =_xludf.XLOOKUP(E6,Sales_Reps!$A$4:$A$11,Sales_Reps!$B$4:$B$11,"Not found") -> #NAME? | T6: =_xludf.XLOOKUP(E6,Sales_Reps!$A$4:$A$11,Sales_Reps!$C$4:$C$11,"Not found") -> #NAME?
A7: O00004 | B7: 46164 | C7: C008 | D7: P008 | E7: R007 | F7: 1 | G7: 900 | H7: 0.1 | I7: 810 | J7: 567 | K7: Closed Won | L7: =_xludf.XLOOKUP(C7,Customers!$A$4:$A$53,Customers!$B$4:$B$53,"Not found") -> #NAME? | M7: =_xludf.XLOOKUP(C7,Customers!$A$4:$A$53,Customers!$C$4:$C$53,"Not found") -> #NAME? | N7: =_xludf.XLOOKUP(C7,Customers!$A$4:$A$53,Customers!$D$4:$D$53,"Not found") -> #NAME? | O7: =_xludf.XLOOKUP(C7,Customers!$A$4:$A$53,Customers!$E$4:$E$53,"Not found") -> #NAME? | P7: =_xludf.XLOOKUP(C7,Customers!$A$4:$A$53,Customers!$F$4:$F$53,"Not found") -> #NAME? | Q7: =_xludf.XLOOKUP(D7,Products!$A$4:$A$23,Products!$B$4:$B$23,"Not found") -> #NAME? | R7: =_xludf.XLOOKUP(D7,Products!$A$4:$A$23,Products!$C$4:$C$23,"Not found") -> #NAME? | S7: =_xludf.XLOOKUP(E7,Sales_Reps!$A$4:$A$11,Sales_Reps!$B$4:$B$11,"Not found") -> #NAME? | T7: =_xludf.XLOOKUP(E7,Sales_Reps!$A$4:$A$11,Sales_Reps!$C$4:$C$11,"Not found") -> #NAME?
A8: O00005 | B8: 46031 | C8: C038 | D8: P008 | E8: R001 | F8: 4 | G8: 900 | H8: 0 | I8: 3600 | J8: 2520 | K8: Closed Won | L8: =_xludf.XLOOKUP(C8,Customers!$A$4:$A$53,Customers!$B$4:$B$53,"Not found") -> #NAME? | M8: =_xludf.XLOOKUP(C8,Customers!$A$4:$A$53,Customers!$C$4:$C$53,"Not found") -> #NAME? | N8: =_xludf.XLOOKUP(C8,Customers!$A$4:$A$53,Customers!$D$4:$D$53,"Not found") -> #NAME? | O8: =_xludf.XLOOKUP(C8,Customers!$A$4:$A$53,Customers!$E$4:$E$53,"Not found") -> #NAME? | P8: =_xludf.XLOOKUP(C8,Customers!$A$4:$A$53,Customers!$F$4:$F$53,"Not found") -> #NAME? | Q8: =_xludf.XLOOKUP(D8,Products!$A$4:$A$23,Products!$B$4:$B$23,"Not found") -> #NAME? | R8: =_xludf.XLOOKUP(D8,Products!$A$4:$A$23,Products!$C$4:$C$23,"Not found") -> #NAME? | S8: =_xludf.XLOOKUP(E8,Sales_Reps!$A$4:$A$11,Sales_Reps!$B$4:$B$11,"Not found") -> #NAME? | T8: =_xludf.XLOOKUP(E8,Sales_Reps!$A$4:$A$11,Sales_Reps!$C$4:$C$11,"Not found") -> #NAME?
A9: O00006 | B9: 46056 | C9: C005 | D9: P017 | E9: R005 | F9: 4 | G9: 2800 | H9: 0.1 | I9: 10080 | J9: 5241.6 | K9: Closed Lost | L9: =_xludf.XLOOKUP(C9,Customers!$A$4:$A$53,Customers!$B$4:$B$53,"Not found") -> #NAME? | M9: =_xludf.XLOOKUP(C9,Customers!$A$4:$A$53,Customers!$C$4:$C$53,"Not found") -> #NAME? | N9: =_xludf.XLOOKUP(C9,Customers!$A$4:$A$53,Customers!$D$4:$D$53,"Not found") -> #NAME? | O9: =_xludf.XLOOKUP(C9,Customers!$A$4:$A$53,Customers!$E$4:$E$53,"Not found") -> #NAME? | P9: =_xludf.XLOOKUP(C9,Customers!$A$4:$A$53,Customers!$F$4:$F$53,"Not found") -> #NAME? | Q9: =_xludf.XLOOKUP(D9,Products!$A$4:$A$23,Products!$B$4:$B$23,"Not found") -> #NAME? | R9: =_xludf.XLOOKUP(D9,Products!$A$4:$A$23,Products!$C$4:$C$23,"Not found") -> #NAME? | S9: =_xludf.XLOOKUP(E9,Sales_Reps!$A$4:$A$11,Sales_Reps!$B$4:$B$11,"Not found") -> #NAME? | T9: =_xludf.XLOOKUP(E9,Sales_Reps!$A$4:$A$11,Sales_Reps!$C$4:$C$11,"Not found") -> #NAME?
A10: O00007 | B10: 46047 | C10: C037 | D10: P016 | E10: R006 | F10: 7 | G10: 1100 | H10: 0 | I10: 7700 | J10: 5236 | K10: Closed Won | L10: =_xludf.XLOOKUP(C10,Customers!$A$4:$A$53,Customers!$B$4:$B$53,"Not found") -> #NAME? | M10: =_xludf.XLOOKUP(C10,Customers!$A$4:$A$53,Customers!$C$4:$C$53,"Not found") -> #NAME? | N10: =_xludf.XLOOKUP(C10,Customers!$A$4:$A$53,Customers!$D$4:$D$53,"Not found") -> #NAME? | O10: =_xludf.XLOOKUP(C10,Customers!$A$4:$A$53,Customers!$E$4:$E$53,"Not found") -> #NAME? | P10: =_xludf.XLOOKUP(C10,Customers!$A$4:$A$53,Customers!$F$4:$F$53,"Not found") -> #NAME? | Q10: =_xludf.XLOOKUP(D10,Products!$A$4:$A$23,Products!$B$4:$B$23,"Not found") -> #NAME? | R10: =_xludf.XLOOKUP(D10,Products!$A$4:$A$23,Products!$C$4:$C$23,"Not found") -> #NAME? | S10: =_xludf.XLOOKUP(E10,Sales_Reps!$A$4:$A$11,Sales_Reps!$B$4:$B$11,"Not found") -> #NAME? | T10: =_xludf.XLOOKUP(E10,Sales_Reps!$A$4:$A$11,Sales_Reps!$C$4:$C$11,"Not found") -> #NAME?
A11: O00008 | B11: 46036 | C11: C043 | D11: P014 | E11: R007 | F11: 8 | G11: 650 | H11: 0.15 | I11: 4420 | J11: 1414.4 | K11: Closed Won | L11: =_xludf.XLOOKUP(C11,Customers!$A$4:$A$53,Customers!$B$4:$B$53,"Not found") -> #NAME? | M11: =_xludf.XLOOKUP(C11,Customers!$A$4:$A$53,Customers!$C$4:$C$53,"Not found") -> #NAME? | N11: =_xludf.XLOOKUP(C11,Customers!$A$4:$A$53,Customers!$D$4:$D$53,"Not found") -> #NAME? | O11: =_xludf.XLOOKUP(C11,Customers!$A$4:$A$53,Customers!$E$4:$E$53,"Not found") -> #NAME? | P11: =_xludf.XLOOKUP(C11,Customers!$A$4:$A$53,Customers!$F$4:$F$53,"Not found") -> #NAME? | Q11: =_xludf.XLOOKUP(D11,Products!$A$4:$A$23,Products!$B$4:$B$23,"Not found") -> #NAME? | R11: =_xludf.XLOOKUP(D11,Products!$A$4:$A$23,Products!$C$4:$C$23,"Not found") -> #NAME? | S11: =_xludf.XLOOKUP(E11,Sales_Reps!$A$4:$A$11,Sales_Reps!$B$4:$B$11,"Not found") -> #NAME? | T11: =_xludf.XLOOKUP(E11,Sales_Reps!$A$4:$A$11,Sales_Reps!$C$4:$C$11,"Not found") -> #NAME?
A12: O00009 | B12: 46071 | C12: C004 | D12: P013 | E12: R001 | F12: 4 | G12: 800 | H12: 0 | I12: 3200 | J12: 864 | K12: Closed Lost | L12: =_xludf.XLOOKUP(C12,Customers!$A$4:$A$53,Customers!$B$4:$B$53,"Not found") -> #NAME? | M12: =_xludf.XLOOKUP(C12,Customers!$A$4:$A$53,Customers!$C$4:$C$53,"Not found") -> #NAME? | N12: =_xludf.XLOOKUP(C12,Customers!$A$4:$A$53,Customers!$D$4:$D$53,"Not found") -> #NAME? | O12: =_xludf.XLOOKUP(C12,Customers!$A$4:$A$53,Customers!$E$4:$E$53,"Not found") -> #NAME? | P12: =_xludf.XLOOKUP(C12,Customers!$A$4:$A$53,Customers!$F$4:$F$53,"Not found") -> #NAME? | Q12: =_xludf.XLOOKUP(D12,Products!$A$4:$A$23,Products!$B$4:$B$23,"Not found") -> #NAME? | R12: =_xludf.XLOOKUP(D12,Products!$A$4:$A$23,Products!$C$4:$C$23,"Not found") -> #NAME? | S12: =_xludf.XLOOKUP(E12,Sales_Reps!$A$4:$A$11,Sales_Reps!$B$4:$B$11,"Not found") -> #NAME? | T12: =_xludf.XLOOKUP(E12,Sales_Reps!$A$4:$A$11,Sales_Reps!$C$4:$C$11,"Not found") -> #NAME?
A13: O00010 | B13: 46042 | C13: C029 | D13: P005 | E13: R006 | F13: 8 | G13: 35 | H13: 0 | I13: 280 | J13: 117.6 | K13: Open | L13: =_xludf.XLOOKUP(C13,Customers!$A$4:$A$53,Customers!$B$4:$B$53,"Not found") -> #NAME? | M13: =_xludf.XLOOKUP(C13,Customers!$A$4:$A$53,Customers!$C$4:$C$53,"Not found") -> #NAME? | N13: =_xludf.XLOOKUP(C13,Customers!$A$4:$A$53,Customers!$D$4:$D$53,"Not found") -> #NAME? | O13: =_xludf.XLOOKUP(C13,Customers!$A$4:$A$53,Customers!$E$4:$E$53,"Not found") -> #NAME? | P13: =_xludf.XLOOKUP(C13,Customers!$A$4:$A$53,Customers!$F$4:$F$53,"Not found") -> #NAME? | Q13: =_xludf.XLOOKUP(D13,Products!$A$4:$A$23,Products!$B$4:$B$23,"Not found") -> #NAME? | R13: =_xludf.XLOOKUP(D13,Products!$A$4:$A$23,Products!$C$4:$C$23,"Not found") -> #NAME? | S13: =_xludf.XLOOKUP(E13,Sales_Reps!$A$4:$A$11,Sales_Reps!$B$4:$B$11,"Not found") -> #NAME? | T13: =_xludf.XLOOKUP(E13,Sales_Reps!$A$4:$A$11,Sales_Reps!$C$4:$C$11,"Not found") -> #NAME?
A14: O00011 | B14: 46065 | C14: C036 | D14: P004 | E14: R001 | F14: 2 | G14: 70 | H14: 0 | I14: 140 | J14: 56 | K14: Open | L14: =_xludf.XLOOKUP(C14,Customers!$A$4:$A$53,Customers!$B$4:$B$53,"Not found") -> #NAME? | M14: =_xludf.XLOOKUP(C14,Customers!$A$4:$A$53,Customers!$C$4:$C$53,"Not found") -> #NAME? | N14: =_xludf.XLOOKUP(C14,Customers!$A$4:$A$53,Customers!$D$4:$D$53,"Not found") -> #NAME? | O14: =_xludf.XLOOKUP(C14,Customers!$A$4:$A$53,Customers!$E$4:$E$53,"Not found") -> #NAME? | P14: =_xludf.XLOOKUP(C14,Customers!$A$4:$A$53,Customers!$F$4:$F$53,"Not found") -> #NAME? | Q14: =_xludf.XLOOKUP(D14,Products!$A$4:$A$23,Products!$B$4:$B$23,"Not found") -> #NAME? | R14: =_xludf.XLOOKUP(D14,Products!$A$4:$A$23,Products!$C$4:$C$23,"Not found") -> #NAME? | S14: =_xludf.XLOOKUP(E14,Sales_Reps!$A$4:$A$11,Sales_Reps!$B$4:$B$11,"Not found") -> #NAME? | T14: =_xludf.XLOOKUP(E14,Sales_Reps!$A$4:$A$11,Sales_Reps!$C$4:$C$11,"Not found") -> #NAME?
A15: O00012 | B15: 46120 | C15: C032 | D15: P016 | E15: R006 | F15: 1 | G15: 1100 | H15: 0 | I15: 1100 | J15: 748 | K15: Closed Won | L15: =_xludf.XLOOKUP(C15,Customers!$A$4:$A$53,Customers!$B$4:$B$53,"Not found") -> #NAME? | M15: =_xludf.XLOOKUP(C15,Customers!$A$4:$A$53,Customers!$C$4:$C$53,"Not found") -> #NAME? | N15: =_xludf.XLOOKUP(C15,Customers!$A$4:$A$53,Customers!$D$4:$D$53,"Not found") -> #NAME? | O15: =_xludf.XLOOKUP(C15,Customers!$A$4:$A$53,Customers!$E$4:$E$53,"Not found") -> #NAME? | P15: =_xludf.XLOOKUP(C15,Customers!$A$4:$A$53,Customers!$F$4:$F$53,"Not found") -> #NAME? | Q15: =_xludf.XLOOKUP(D15,Products!$A$4:$A$23,Products!$B$4:$B$23,"Not found") -> #NAME? | R15: =_xludf.XLOOKUP(D15,Products!$A$4:$A$23,Products!$C$4:$C$23,"Not found") -> #NAME? | S15: =_xludf.XLOOKUP(E15,Sales_Reps!$A$4:$A$11,Sales_Reps!$B$4:$B$11,"Not found") -> #NAME? | T15: =_xludf.XLOOKUP(E15,Sales_Reps!$A$4:$A$11,Sales_Reps!$C$4:$C$11,"Not found") -> #NAME?
... A183: O00180 | B183: 46058 | C183: C030 | D183: P010 | E183: R007 | F183: 3 | G183: 1200 | H183: 0 | I183: 3600 | J183: 2160 | K183: Closed Won | L183: =_xludf.XLOOKUP(C183,Customers!$A$4:$A$53,Customers!$B$4:$B$53,"Not found") -> #NAME? | M183: =_xludf.XLOOKUP(C183,Customers!$A$4:$A$53,Customers!$C$4:$C$53,"Not found") -> #NAME? | N183: =_xludf.XLOOKUP(C183,Customers!$A$4:$A$53,Customers!$D$4:$D$53,"Not found") -> #NAME? | O183: =_xludf.XLOOKUP(C183,Customers!$A$4:$A$53,Customers!$E$4:$E$53,"Not found") -> #NAME? | P183: =_xludf.XLOOKUP(C183,Customers!$A$4:$A$53,Customers!$F$4:$F$53,"Not found") -> #NAME? | Q183: =_xludf.XLOOKUP(D183,Products!$A$4:$A$23,Products!$B$4:$B$23,"Not found") -> #NAME? | R183: =_xludf.XLOOKUP(D183,Products!$A$4:$A$23,Products!$C$4:$C$23,"Not found") -> #NAME? | S183: =_xludf.XLOOKUP(E183,Sales_Reps!$A$4:$A$11,Sales_Reps!$B$4:$B$11,"Not found") -> #NAME? | T183: =_xludf.XLOOKUP(E183,Sales_Reps!$A$4:$A$11,Sales_Reps!$C$4:$C$11,"Not found") -> #NAME?

Sheet XLOOKUP_Module
A1: Module 1: XLOOKUP — Connect Related Tables
A3: Business Problem | B3: Orders have Customer ID, Product ID, and Rep ID, but the business wants readable names and details.
A4: Goal | B4: Use XLOOKUP to populate Customer Name, Industry, Product Name, and Sales Rep in Orders_Practice.
A5: Mental Model | B5: Look up a value in one table and return matching information from another table using a shared field.
A9: Exercise | B9: Business Request | C9: Shared Field | D9: Lookup Table | E9: Return Field | F9: Where to Enter Formula | G9: Hint | H9: Done?
A10: 1 | B10: Bring Customer Name into Orders | C10: Customer ID | D10: Customers | E10: Customer Name | F10: Orders_Practice!L4 | G10: =_xludf.XLOOKUP(C4, Customers ID column, Customer Name column) -> #NAME?
A11: 2 | B11: Bring State into Orders | C11: Customer ID | D11: Customers | E11: State | F11: Orders_Practice!M4 | G11: Same lookup value, different return column
A12: 3 | B12: Bring Industry into Orders | C12: Customer ID | D12: Customers | E12: Industry | F12: Orders_Practice!O4 | G12: Use Customers Industry column as return array
A13: 4 | B13: Bring Product Name into Orders | C13: Product ID | D13: Products | E13: Product Name | F13: Orders_Practice!Q4 | G13: Use Product ID as shared field
A14: 5 | B14: Bring Sales Rep Name into Orders | C14: Rep ID | D14: Sales_Reps | E14: Sales Rep | F14: Orders_Practice!S4 | G14: Use Rep ID as shared field
A17: Interview Practice
A18: Prompt | B18: Answer in your own words
A19: What business problem does XLOOKUP solve?
A20: How is XLOOKUP similar to Salesforce relationships?

Sheet SUMIFS_Module
A1: Module 2: SUMIFS — Add Numbers That Meet Conditions
A3: Business Problem | B3: Leadership wants revenue totals by region, industry, product, or rep without manually filtering.
A4: Goal | B4: Use SUMIFS to calculate revenue and profit for specific business conditions.
A5: Mental Model | B5: What am I summing? Under what condition?
A9: Exercise | B9: Business Request | C9: Sum Range | D9: Criteria Range | E9: Criteria | F9: Formula Cell | G9: Hint | H9: Answer Check
A10: 1 | B10: Total Revenue for North region | C10: Orders_Solution!Revenue | D10: Orders_Solution!Region | E10: North | F10: B18 | G10: Sum Revenue where Region = North
A11: 2 | B11: Total Revenue for Technology industry | C11: Orders_Solution!Revenue | D11: Orders_Solution!Industry | E11: Technology | F11: B19 | G11: Use lookup-generated Industry column
A12: 3 | B12: Total Profit for Hardware category | C12: Orders_Solution!Profit | D12: Orders_Solution!Category | E12: Hardware | F12: B20 | G12: Sum Profit where Category = Hardware
A13: 4 | B13: Total Revenue for Sales Rep Ava Johnson | C13: Orders_Solution!Revenue | D13: Orders_Solution!Sales Rep | E13: Ava Johnson | F13: B21 | G13: Sum Revenue where Sales Rep = Ava Johnson
A17: Practice Summary | B17: Formula | C17: Result
A18: North Revenue | B18: =SUMIFS(Orders_Solution!$I$4:$I$183,Orders_Solution!$N$4:$N$183,"North") -> 0 | C18: Use your own formula first, then compare
A19: Technology Revenue | B19: =SUMIFS(Orders_Solution!$I$4:$I$183,Orders_Solution!$O$4:$O$183,"Technology") -> 0
A20: Hardware Profit | B20: =SUMIFS(Orders_Solution!$J$4:$J$183,Orders_Solution!$R$4:$R$183,"Hardware") -> 0
A21: Ava Johnson Revenue | B21: =SUMIFS(Orders_Solution!$I$4:$I$183,Orders_Solution!$S$4:$S$183,"Ava Johnson") -> 0

Sheet COUNTIFS_Module
A1: Module 3: COUNTIFS — Count Records That Meet Conditions
A3: Business Problem | B3: Managers want to know how many orders meet specific conditions.
A4: Goal | B4: Use COUNTIFS to count orders by region, product category, status, and rep.
A5: Mental Model | B5: What am I counting? What conditions must be true?
A9: Exercise | B9: Business Request | C9: Criteria Range 1 | D9: Criteria 1 | E9: Criteria Range 2 | F9: Criteria 2 | G9: Formula Cell | H9: Hint
A10: 1 | B10: Count North region orders | C10: Region | D10: North | G10: B18 | H10: One condition
A11: 2 | B11: Count Closed Won orders | C11: Status | D11: Closed Won | G11: B19 | H11: One condition
A12: 3 | B12: Count Hardware orders in North | C12: Category | D12: Hardware | E12: Region | F12: North | G12: B20 | H12: Two conditions
A13: 4 | B13: Count orders assigned to Ava Johnson | C13: Sales Rep | D13: Ava Johnson | G13: B21 | H13: Use lookup-generated Sales Rep
A17: Practice Summary | B17: Formula / Result
A18: North Orders | B18: =COUNTIFS(Orders_Solution!$N$4:$N$183,"North") -> 0
A19: Closed Won Orders | B19: =COUNTIFS(Orders_Solution!$K$4:$K$183,"Closed Won") -> 102
A20: Hardware Orders in North | B20: =COUNTIFS(Orders_Solution!$R$4:$R$183,"Hardware",Orders_Solution!$N$4:$N$183,"North") -> 0
A21: Ava Johnson Orders | B21: =COUNTIFS(Orders_Solution!$S$4:$S$183,"Ava Johnson") -> 0

Sheet Conditional_Formatting
A1: Module 4: Conditional Formatting — Spot Exceptions Fast
A3: Business Problem | B3: Managers need to quickly identify high-value orders, missing lookup values, and negative outcomes.
A4: Goal | B4: Use visual rules to highlight important records without manually scanning rows.
A8: Exercise | B8: Business Request | C8: Where to Apply | D8: Rule Type | E8: Condition | F8: Recommended Format | G8: Business Why | H8: Done?
A9: 1 | B9: Highlight revenue over $5,000 | C9: Orders_Practice!I:I | D9: Cell Value | E9: > 5000 | F9: Green fill | G9: High-value transactions deserve attention
A10: 2 | B10: Highlight missing Customer Names | C10: Orders_Practice!L:L | D10: Blank cells | E10: Is blank | F10: Red fill | G10: Missing data can break reports
A11: 3 | B11: Highlight Closed Lost orders | C11: Orders_Practice!K:K | D11: Text contains | E11: Closed Lost | F11: Light red fill | G11: Lost deals may need review
A12: 4 | B12: Highlight discount over 10% | C12: Orders_Practice!H:H | D12: Cell Value | E12: > 10% | F12: Yellow fill | G12: Large discounts can reduce profit

Sheet PivotTables_Module
A1: Module 5: PivotTables — Summarize Business Performance
A3: Business Problem | B3: Leadership needs a fast way to summarize revenue, profit, and order volume.
A4: Goal | B4: Use PivotTables to answer business questions without manually sorting or filtering data.
A5: Mental Model | B5: Rows = what am I grouping by? Values = what am I calculating? Filters = what do I want to choose?
A9: Exercise | B9: Business Question | C9: Rows | D9: Values | E9: Filters | F9: Columns | G9: Business Insight to Write | H9: Done?
A10: 1 | B10: Revenue by Region | C10: Region | D10: Revenue | G10: Which region generated the most revenue?
A11: 2 | B11: Revenue by Sales Rep | C11: Sales Rep | D11: Revenue | G11: Which rep generated the most revenue?
A12: 3 | B12: Profit by Product Category | C12: Category | D12: Profit | G12: Which category is most profitable?
A13: 4 | B13: Revenue by Region filtered by Industry | C13: Region | D13: Revenue | E13: Industry | G13: How does filtering change the story?

Sheet Executive_Dashboard
A1: Executive Dashboard Starter
A3: KPI | B3: Value | D3: Region | E3: Revenue
A4: Total Revenue | B4: =SUM(Orders_Solution!I4:I183) -> 815443.75 | D4: North | E4: =SUMIFS(Orders_Solution!$I$4:$I$183,Orders_Solution!$N$4:$N$183,D4) -> 0
A5: Total Profit | B5: =SUM(Orders_Solution!J4:J183) -> 382859.93 | D5: South | E5: =SUMIFS(Orders_Solution!$I$4:$I$183,Orders_Solution!$N$4:$N$183,D5) -> 0
A6: Order Count | B6: =COUNTA(Orders_Solution!A4:A183) -> 180 | D6: East | E6: =SUMIFS(Orders_Solution!$I$4:$I$183,Orders_Solution!$N$4:$N$183,D6) -> 0
A7: Avg Order Revenue | B7: =AVERAGE(Orders_Solution!I4:I183) -> 4530.2431 | D7: West | E7: =SUMIFS(Orders_Solution!$I$4:$I$183,Orders_Solution!$N$4:$N$183,D7) -> 0
A8: Closed Won Orders | B8: =COUNTIFS(Orders_Solution!K4:K183,"Closed Won") -> 102

Sheet Interview_Journal
A1: Interview Journal
A3: Concept | B3: Business Problem | C3: Solution | D3: Business Value | E3: 30-Second Answer | F3: Project Evidence
A4: XLOOKUP | B4: Manual copy/paste creates errors | C4: Retrieve related data using shared IDs | D4: Saves time and improves accuracy | F4: Orders + Customers tables
A5: SUMIFS | B5: Need totals by condition | C5: Sum values that meet criteria | D5: Supports fast business reporting | F5: Revenue by region/industry
A6: COUNTIFS | B6: Need to count records by criteria | C6: Count rows that meet one or more conditions | D6: Helps measure activity volume | F6: Orders by status/region
A7: Conditional Formatting | B7: Need to spot exceptions quickly | C7: Automatically highlight important values | D7: Improves visibility and reduces review time | F7: High-value order flags
A8: PivotTables | B8: Need to summarize large data | C8: Group and calculate metrics | D8: Turns raw data into insight | F8: Revenue by region/rep

Sheet Reflection
A1: Reflection — What Did I Learn?
A3: Date | B3: Topic | C3: In My Own Words | D3: Business Problem It Solves | E3: Where I Used It | F3: Confidence 1-5

Sheet Answer_Key
A1: Answer Key and Formula Examples
A3: Topic | B3: Example Formula | C3: Plain English | D3: Notes
A4: XLOOKUP Customer Name | B4: =_xludf.XLOOKUP(C4,Customers!$A$4:$A$53,Customers!$B$4:$B$53,"Not found") -> #NAME? | C4: Find Customer ID and return Customer Name | D4: Use in Orders_Practice L4
A5: XLOOKUP Product Name | B5: =_xludf.XLOOKUP(D4,Products!$A$4:$A$23,Products!$B$4:$B$23,"Not found") -> #NAME? | C5: Find Product ID and return Product Name | D5: Use in Orders_Practice Q4
A6: SUMIFS North Revenue | B6: =SUMIFS(Orders_Solution!$I$4:$I$183,Orders_Solution!$N$4:$N$183,"North") -> 0 | C6: Add Revenue when Region is North
A7: COUNTIFS Closed Won | B7: =COUNTIFS(Orders_Solution!$K$4:$K$183,"Closed Won") -> 102 | C7: Count orders with Closed Won status
